Metadata-Version: 2.1
Name: invoicing-anindya
Version: 1.0.0
Summary: This package can convert a particular format of excel invoices to pdfs. This is an example package from Ardit Sulce's course
Home-page: https://example.com
Author: Anindya Dey
Author-email: email@example.com
License: MIT
Keywords: invoice,excel,pdf
Classifier: Development Status :: 4 - Beta
Classifier: Intended Audience :: Developers
Classifier: Topic :: Software Development :: Build Tools
Classifier: License :: OSI Approved :: MIT License
Classifier: Programming Language :: Python :: 3.8
Classifier: Programming Language :: Python :: 3.9
Classifier: Programming Language :: Python :: 3.10
Classifier: Programming Language :: Python :: 3.11
Requires-Dist: fpdf
Requires-Dist: openpyxl
Requires-Dist: pandas
